ethiopian_date_sdk/__init__.py
ethiopian_date_sdk/converter.py
ethiopian_date_sdk-1.0.0.dist-info/METADATA
ethiopian_date_sdk-1.0.0.dist-info/WHEEL
ethiopian_date_sdk-1.0.0.dist-info/licence
ethiopian_date_sdk-1.0.0.dist-info/top_level.txt
ethiopian_date_sdk-1.0.0.dist-info/RECORD
