Metadata-Version: 2.2
Name: ethiopian_date_sdk
Version: 1.0.0
Summary: A Python SDK for converting dates between the Ethiopian and Gregorian calendars.
Author: Zelalem Tamrie
Author-email: zelalem.t8@gmail.com
Classifier: Programming Language :: Python :: 3
Classifier: License :: OSI Approved :: MIT License
Classifier: Operating System :: OS Independent
Requires-Python: >=3.6
License-File: licence
Dynamic: author
Dynamic: author-email
Dynamic: classifier
Dynamic: requires-python
Dynamic: summary
